uniprot.py
uniprot-1.4.1.dist-info/METADATA
uniprot-1.4.1.dist-info/WHEEL
uniprot-1.4.1.dist-info/entry_points.txt
uniprot-1.4.1.dist-info/RECORD
