Metadata-Version: 2.4
Name: uniprot
Version: 1.4.1
Summary: retrieve protein sequence identifiers and metadata from http://uniprot.org
Project-URL: Repository, http://github.com/boscoh/uniprot
Author-email: Bosco Ho <boscoh@gmail.com>
License: BSD
Keywords: bioinformatics,identifier,protein,sequence,uniprot
Classifier: Development Status :: 4 - Beta
Classifier: Intended Audience :: Science/Research
Classifier: License :: OSI Approved :: BSD License
Classifier: Programming Language :: Python
Classifier: Programming Language :: Python :: 3
Classifier: Programming Language :: Python :: 3.8
Classifier: Programming Language :: Python :: 3.9
Classifier: Programming Language :: Python :: 3.10
Classifier: Programming Language :: Python :: 3.11
Classifier: Programming Language :: Python :: 3.12
Classifier: Topic :: Scientific/Engineering :: Bio-Informatics
Requires-Python: >=3.8
Requires-Dist: httpx>=0.24.0
